[{"x":300,"y":162,"width":125,"height":211,"frameIndex":0,"row":0,"col":0,"originalX":300,"originalY":162},{"x":422,"y":162,"width":121,"height":211,"frameIndex":1,"row":0,"col":1,"originalX":301,"originalY":162},{"x":517,"y":161,"width":105,"height":212,"frameIndex":2,"row":0,"col":2,"originalX":307,"originalY":161},{"x":567,"y":161,"width":83,"height":212,"frameIndex":3,"row":0,"col":3,"originalX":318,"originalY":161},{"x":321,"y":373,"width":75,"height":212,"frameIndex":4,"row":1,"col":0,"originalX":321,"originalY":161},{"x":387,"y":373,"width":66,"height":213,"frameIndex":5,"row":1,"col":1,"originalX":321,"originalY":160},{"x":453,"y":373,"width":66,"height":214,"frameIndex":6,"row":1,"col":2,"originalX":321,"originalY":159},{"x":564,"y":373,"width":81,"height":214,"frameIndex":7,"row":1,"col":3,"originalX":321,"originalY":159},{"x":321,"y":586,"width":97,"height":213,"frameIndex":8,"row":2,"col":0,"originalX":321,"originalY":160},{"x":422,"y":585,"width":105,"height":212,"frameIndex":9,"row":2,"col":1,"originalX":317,"originalY":161},{"x":546,"y":581,"width":119,"height":209,"frameIndex":10,"row":2,"col":2,"originalX":308,"originalY":163},{"x":673,"y":580,"width":123,"height":208,"frameIndex":11,"row":2,"col":3,"originalX":304,"originalY":164},{"x":297,"y":786,"width":130,"height":207,"frameIndex":12,"row":3,"col":0,"originalX":297,"originalY":165},{"x":425,"y":786,"width":132,"height":207,"frameIndex":13,"row":3,"col":1,"originalX":293,"originalY":165},{"x":553,"y":791,"width":130,"height":209,"frameIndex":14,"row":3,"col":2,"originalX":293,"originalY":164},{"x":652,"y":790,"width":118,"height":209,"frameIndex":15,"row":3,"col":3,"originalX":298,"originalY":163},{"x":310,"y":1002,"width":97,"height":210,"frameIndex":16,"row":4,"col":0,"originalX":310,"originalY":162},{"x":403,"y":1005,"width":86,"height":211,"frameIndex":17,"row":4,"col":1,"originalX":317,"originalY":161},{"x":464,"y":1009,"width":71,"height":212,"frameIndex":18,"row":4,"col":2,"originalX":322,"originalY":161},{"x":522,"y":1012,"width":67,"height":213,"frameIndex":19,"row":4,"col":3,"originalX":321,"originalY":160},{"x":321,"y":1225,"width":75,"height":213,"frameIndex":20,"row":5,"col":0,"originalX":321,"originalY":160},{"x":414,"y":1220,"width":94,"height":212,"frameIndex":21,"row":5,"col":1,"originalX":320,"originalY":160},{"x":522,"y":1220,"width":101,"height":212,"frameIndex":22,"row":5,"col":2,"originalX":320,"originalY":160},{"x":668,"y":1212,"width":118,"height":210,"frameIndex":23,"row":5,"col":3,"originalX":314,"originalY":162},{"x":305,"y":1417,"width":131,"height":209,"frameIndex":24,"row":6,"col":0,"originalX":305,"originalY":163},{"x":436,"y":1412,"width":133,"height":208,"frameIndex":25,"row":6,"col":1,"originalX":303,"originalY":164},{"x":567,"y":1418,"width":133,"height":209,"frameIndex":26,"row":6,"col":2,"originalX":301,"originalY":164},{"x":694,"y":1418,"width":131,"height":209,"frameIndex":27,"row":6,"col":3,"originalX":301,"originalY":164}]